<?xml version="1.0" encoding="UTF-8"?>
<objects serializationModel="Studio.01.09.00">
    <object class="Event" id="{ec7623b6-2ae6-431e-ad71-bb07e17356cc}">
        <property name="name">
            <value>Dialogues3</value>
        </property>
        <property name="note">
            <value>2 lines
</value>
        </property>
        <property name="outputFormat">
            <value>0</value>
        </property>
        <relationship name="folder">
            <destination>{b255b7c8-f3e3-46da-938d-04464fc00452}</destination>
        </relationship>
        <relationship name="mixer">
            <destination>{e23c0396-dbf3-40f3-9435-d3e96400d21e}</destination>
        </relationship>
        <relationship name="masterTrack">
            <destination>{cb2bde7e-5c60-4ad2-950e-5dc1ec696f7a}</destination>
        </relationship>
        <relationship name="mixerInput">
            <destination>{70b34b87-d14f-4898-93b7-9d5fc13da981}</destination>
        </relationship>
        <relationship name="automatableProperties">
            <destination>{7a719fb7-e6a6-4419-9bd1-087578e6beb5}</destination>
        </relationship>
        <relationship name="markerTracks">
            <destination>{9ffa83e0-97ff-4adf-a2e2-96349699b977}</destination>
        </relationship>
        <relationship name="groupTracks">
            <destination>{9a6a5c0b-165b-4cb9-b9af-4fe9dcaccfa7}</destination>
        </relationship>
        <relationship name="timeline">
            <destination>{ce7f4d81-dc78-4d42-9054-df7a2b2c411e}</destination>
        </relationship>
        <relationship name="parameters">
            <destination>{b3152815-4dad-4124-8125-652c818b93fb}</destination>
        </relationship>
    </object>
    <object class="EventMixer" id="{e23c0396-dbf3-40f3-9435-d3e96400d21e}">
        <relationship name="masterBus">
            <destination>{76dce89b-55bd-47d9-a0d3-ac1ec669a7ac}</destination>
        </relationship>
    </object>
    <object class="MasterTrack" id="{cb2bde7e-5c60-4ad2-950e-5dc1ec696f7a}">
        <relationship name="mixerGroup">
            <destination>{76dce89b-55bd-47d9-a0d3-ac1ec669a7ac}</destination>
        </relationship>
    </object>
    <object class="MixerInput" id="{70b34b87-d14f-4898-93b7-9d5fc13da981}">
        <relationship name="effectChain">
            <destination>{d842c661-bed9-4761-a8f0-ba90de3fa204}</destination>
        </relationship>
        <relationship name="panner">
            <destination>{48b2dc4a-d20b-4a66-9de5-46ad4dac1a89}</destination>
        </relationship>
    </object>
    <object class="EventAutomatableProperties" id="{7a719fb7-e6a6-4419-9bd1-087578e6beb5}"/>
    <object class="MarkerTrack" id="{9ffa83e0-97ff-4adf-a2e2-96349699b977}"/>
    <object class="GroupTrack" id="{9a6a5c0b-165b-4cb9-b9af-4fe9dcaccfa7}">
        <relationship name="modules">
            <destination>{7ddf52db-99ba-49e5-943e-f6a18d63355b}</destination>
            <destination>{dbc3e3ab-040f-498c-a7c2-e93bb988ddd7}</destination>
        </relationship>
        <relationship name="mixerGroup">
            <destination>{dd62fd08-0696-4293-a594-dbb5d63a92b1}</destination>
        </relationship>
    </object>
    <object class="Timeline" id="{ce7f4d81-dc78-4d42-9054-df7a2b2c411e}"/>
    <object class="GameParameter" id="{b3152815-4dad-4124-8125-652c818b93fb}">
        <property name="name">
            <value>VoiceClip</value>
        </property>
        <property name="maximum">
            <value>20</value>
        </property>
        <relationship name="modules">
            <destination>{7ddf52db-99ba-49e5-943e-f6a18d63355b}</destination>
            <destination>{dbc3e3ab-040f-498c-a7c2-e93bb988ddd7}</destination>
        </relationship>
    </object>
    <object class="EventMixerMaster" id="{76dce89b-55bd-47d9-a0d3-ac1ec669a7ac}">
        <relationship name="effectChain">
            <destination>{821556b4-6209-42b0-909a-260fdd209f98}</destination>
        </relationship>
        <relationship name="panner">
            <destination>{06397e52-d23b-4577-a41f-34108e18f466}</destination>
        </relationship>
        <relationship name="mixer">
            <destination>{e23c0396-dbf3-40f3-9435-d3e96400d21e}</destination>
        </relationship>
    </object>
    <object class="MixerBusEffectChain" id="{d842c661-bed9-4761-a8f0-ba90de3fa204}">
        <relationship name="effects">
            <destination>{61dead10-cc4c-4bbf-9cff-28e3a2f1eda5}</destination>
        </relationship>
    </object>
    <object class="MixerBusPanner" id="{48b2dc4a-d20b-4a66-9de5-46ad4dac1a89}"/>
    <object class="SingleSound" id="{7ddf52db-99ba-49e5-943e-f6a18d63355b}">
        <property name="isCutoff">
            <value>true</value>
        </property>
        <property name="start">
            <value>1.8</value>
        </property>
        <property name="length">
            <value>0.52631578947368407</value>
        </property>
        <relationship name="audioFile">
            <destination>{53b3ab30-aae8-4e9d-b0f1-fd0481b1e762}</destination>
        </relationship>
    </object>
    <object class="SingleSound" id="{dbc3e3ab-040f-498c-a7c2-e93bb988ddd7}">
        <property name="isCutoff">
            <value>true</value>
        </property>
        <property name="start">
            <value>0.80000000000000004</value>
        </property>
        <property name="length">
            <value>0.52631578947368363</value>
        </property>
        <relationship name="audioFile">
            <destination>{a3123b30-a404-4626-bb20-0275963ba381}</destination>
        </relationship>
    </object>
    <object class="EventMixerGroup" id="{dd62fd08-0696-4293-a594-dbb5d63a92b1}">
        <property name="name">
            <value>Audio 1</value>
        </property>
        <relationship name="effectChain">
            <destination>{10b52cbe-bc4e-4c29-acc4-06acb7fa029d}</destination>
        </relationship>
        <relationship name="panner">
            <destination>{8a631d32-6e03-4398-b1b6-8eb0047c000c}</destination>
        </relationship>
        <relationship name="output">
            <destination>{76dce89b-55bd-47d9-a0d3-ac1ec669a7ac}</destination>
        </relationship>
    </object>
    <object class="MixerBusEffectChain" id="{821556b4-6209-42b0-909a-260fdd209f98}">
        <relationship name="effects">
            <destination>{b1f2072b-8663-4ac7-8d27-d0f98bbe5332}</destination>
        </relationship>
    </object>
    <object class="MixerBusPanner" id="{06397e52-d23b-4577-a41f-34108e18f466}"/>
    <object class="MixerBusFader" id="{61dead10-cc4c-4bbf-9cff-28e3a2f1eda5}"/>
    <object class="MixerBusEffectChain" id="{10b52cbe-bc4e-4c29-acc4-06acb7fa029d}">
        <relationship name="effects">
            <destination>{6cb1c536-6fec-49a7-89b4-0cecdf0bf4b2}</destination>
        </relationship>
    </object>
    <object class="MixerBusPanner" id="{8a631d32-6e03-4398-b1b6-8eb0047c000c}"/>
    <object class="MixerBusFader" id="{b1f2072b-8663-4ac7-8d27-d0f98bbe5332}"/>
    <object class="MixerBusFader" id="{6cb1c536-6fec-49a7-89b4-0cecdf0bf4b2}"/>
</objects>
